currentplatform/__init__.py
krozark_current_platform-0.1.0.dist-info/LICENSE
krozark_current_platform-0.1.0.dist-info/METADATA
krozark_current_platform-0.1.0.dist-info/WHEEL
krozark_current_platform-0.1.0.dist-info/top_level.txt
krozark_current_platform-0.1.0.dist-info/RECORD
